Metadata-Version: 2.1
Name: AmNyam
Version: 0.0.1
Summary: My Package
Author: Your Name
Author-email: ksusha98415@gmail.com
